swarmauri_parser_slate/SlateParser.py
swarmauri_parser_slate/__init__.py
swarmauri_parser_slate-0.1.1.dist-info/METADATA
swarmauri_parser_slate-0.1.1.dist-info/WHEEL
swarmauri_parser_slate-0.1.1.dist-info/RECORD
