Metadata-Version: 2.3
Name: swarmauri_parser_slate
Version: 0.1.1
Summary: A parser for extracting text from PDFs using Slate.
License: Apache-2.0
Author: Vijay Vignesh
Author-email: vijayvigneshp02@gmail.com
Requires-Python: >=3.10,<3.13
Classifier: License :: OSI Approved :: Apache Software License
Classifier: Programming Language :: Python :: 3.10
Classifier: Programming Language :: Python :: 3.11
Classifier: Programming Language :: Python :: 3.12
Requires-Dist: slate3k (>=0.5)
Requires-Dist: swarmauri_base
Requires-Dist: swarmauri_core
Requires-Dist: swarmauri_standard
